LoRaRF/SX126x.py
LoRaRF/SX127x.py
LoRaRF/__init__.py
LoRaRF/base.py
LoRaRF-1.4.0.dist-info/LICENSE
LoRaRF-1.4.0.dist-info/METADATA
LoRaRF-1.4.0.dist-info/WHEEL
LoRaRF-1.4.0.dist-info/top_level.txt
LoRaRF-1.4.0.dist-info/RECORD
