Metadata-Version: 2.1
Name: LoRaRF
Version: 1.4.0
Summary: Python library used for basic transmitting and receiving data using LoRa modem
Home-page: https://github.com/chandrawi/LoRaRF-Python
Author: Chandra Wijaya Sentosa
Author-email: chandra.w.sentosa@gmail.com
Project-URL: Bug Tracker, https://github.com/chandrawi/LoRaRF-Python/issues
Classifier: Programming Language :: Python :: 2.7
Classifier: Programming Language :: Python :: 3
Classifier: License :: OSI Approved :: MIT License
Classifier: Operating System :: POSIX :: Linux
Classifier: Topic :: System :: Hardware
Classifier: Topic :: System :: Hardware :: Hardware Drivers
Requires-Python: >=2.7
License-File: LICENSE
